MANIFEST.in
setup.py
bin/sf-view-recording
bin/sf-view-timeseries
spikeforest_widgets/BaseWidget.py
spikeforest_widgets/__init__.py
spikeforest_widgets/_version.py
spikeforest_widgets/all_widgets.py
spikeforest_widgets/host_widget.py
spikeforest_widgets/init.py
spikeforest_widgets/reactopya_serialize.py
spikeforest_widgets/reactopyacolabwidget.py
spikeforest_widgets/reactopyacomponent.py
spikeforest_widgets/reactopyaelectronwidget.py
spikeforest_widgets/reactopyahostedwidget.py
spikeforest_widgets/shellscript.py
spikeforest_widgets.egg-info/PKG-INFO
spikeforest_widgets.egg-info/SOURCES.txt
spikeforest_widgets.egg-info/dependency_links.txt
spikeforest_widgets.egg-info/requires.txt
spikeforest_widgets.egg-info/top_level.txt
spikeforest_widgets/dist/bundle.js
spikeforest_widgets/electron/src/ReactopyaModel.js
spikeforest_widgets/electron/src/index.js
spikeforest_widgets/electron/src/preload.js
spikeforest_widgets/electron/web/index.html
spikeforest_widgets/host_widget/dist/bundle.js
spikeforest_widgets/widgets/__init__.py
spikeforest_widgets/widgets/index.js
spikeforest_widgets/widgets/Analysis/Algorithms.js
spikeforest_widgets/widgets/Analysis/Analysis.js
spikeforest_widgets/widgets/Analysis/Analysis.json
spikeforest_widgets/widgets/Analysis/Analysis.py
spikeforest_widgets/widgets/Analysis/Sorters.js
spikeforest_widgets/widgets/Analysis/Study.js
spikeforest_widgets/widgets/Analysis/StudyAnalysisResults.js
spikeforest_widgets/widgets/Analysis/StudySets.js
spikeforest_widgets/widgets/Analysis/__init__.py
spikeforest_widgets/widgets/Analysis/__pycache__/Analysis.cpython-37.pyc
spikeforest_widgets/widgets/Analysis/__pycache__/__init__.cpython-37.pyc
spikeforest_widgets/widgets/ElectrodeGeometry/ElectrodeGeometry.js
spikeforest_widgets/widgets/ElectrodeGeometry/ElectrodeGeometry.json
spikeforest_widgets/widgets/ElectrodeGeometry/ElectrodeGeometry.py
spikeforest_widgets/widgets/ElectrodeGeometry/ElectrodeGeometryWidget.js
spikeforest_widgets/widgets/ElectrodeGeometry/__init__.py
spikeforest_widgets/widgets/ElectrodeGeometry/__pycache__/ElectrodeGeometry.cpython-37.pyc
spikeforest_widgets/widgets/ElectrodeGeometry/__pycache__/__init__.cpython-37.pyc
